{
  "DevOps Fundamentals": {
    "aiRubric": "Check basic bash commands, networking concepts, cloud provider basics, IAM setup, and CI/CD logic.",
    "lessons": [
      {
        "title": "Linux Command Line & Bash Scripting",
        "theory": "## Bash Scripting\nBash is the default shell for many Linux distros.\n```bash\n#!/bin/bash\necho \"Starting script...\"\nls -la /var/www\n```",
        "instructions": "## Task: Simple Script\nWrite a bash script that prints 'Hello DevOps' and then lists the contents of the current directory.",
        "starterCode": "#!/bin/bash\n\n___ \"Hello DevOps\"\n___ -la\n",
        "solution": "#!/bin/bash\necho \"Hello DevOps\"\nls -la\n",
        "hint": "Use echo and ls -la.",
        "rubric": "echo and ls commands used correctly."
      },
      {
        "title": "Networking Basics (IP, DNS, HTTP)",
        "theory": "## DNS & HTTP\nDNS resolves domains to IPs. HTTP is the protocol of the web.\n```bash\ncurl -I https://api.github.com\n```",
        "instructions": "## Task: Curl Headers\nUse `curl` to fetch only the HTTP headers from `http://example.com`.",
        "starterCode": "___ -I http://example.com",
        "solution": "curl -I http://example.com",
        "hint": "curl -I",
        "rubric": "curl -I command correctly structured."
      },
      {
        "title": "Introduction to Cloud Providers (AWS & Azure)",
        "theory": "## Cloud Providers\nAWS uses CLI commands like `aws s3 ls`.\n```bash\naws ec2 describe-instances\n```",
        "instructions": "## Task: AWS CLI\nWrite the AWS CLI command to list all S3 buckets.",
        "starterCode": "aws ___ ___",
        "solution": "aws s3 ls",
        "hint": "aws s3 ls",
        "rubric": "aws s3 ls invoked."
      },
      {
        "title": "Identity & Access Management (IAM)",
        "theory": "## IAM Policies\nIAM defines permissions using JSON policies.\n```json\n{\n  \"Effect\": \"Allow\",\n  \"Action\": \"s3:ListBucket\",\n  \"Resource\": \"*\"\n}\n```",
        "instructions": "## Task: IAM JSON\nComplete the IAM policy to `Allow` the action `ec2:DescribeInstances`.",
        "starterCode": "{\n  \"Effect\": \"___\",\n  \"Action\": \"___\",\n  \"Resource\": \"*\"\n}",
        "solution": "{\n  \"Effect\": \"Allow\",\n  \"Action\": \"ec2:DescribeInstances\",\n  \"Resource\": \"*\"\n}",
        "hint": "Allow and ec2:DescribeInstances",
        "rubric": "IAM policy JSON is correct."
      },
      {
        "title": "CI/CD Pipelines (GitHub Actions)",
        "theory": "## GitHub Actions\nAutomate workflows using YAML.\n```yaml\nname: CI\non: [push]\njobs:\n  build:\n    runs-on: ubuntu-latest\n```",
        "instructions": "## Task: Trigger Action\nConfigure the GitHub Action workflow to trigger `on: [pull_request]`.",
        "starterCode": "name: CI\non: [___]\njobs:\n  test:\n    runs-on: ubuntu-latest",
        "solution": "name: CI\non: [pull_request]\njobs:\n  test:\n    runs-on: ubuntu-latest",
        "hint": "on: [pull_request]",
        "rubric": "GitHub Action triggers on pull_request."
      },
      {
        "title": "Core Concepts of DevOps Fundamentals",
        "theory": "## Understanding DevOps Fundamentals\\nBefore diving into complex implementations, it's essential to understand the foundational principles of DevOps Fundamentals.",
        "instructions": "## Task: Define Core Concept\\n1. Create a function `get_concept()` that returns the string 'DevOps Fundamentals Foundation'.",
        "starterCode": "def get_concept():\\n    return '___'",
        "solution": "def get_concept():\\n    return 'DevOps Fundamentals Foundation'",
        "hint": "Return the exact string 'DevOps Fundamentals Foundation'.",
        "rubric": "Function returns the correct concept string."
      },
      {
        "title": "Setting up the Environment for DevOps Fundamentals",
        "theory": "## Tooling\\nProperly configuring your development environment is the first step in mastering DevOps Fundamentals.",
        "instructions": "## Task: Environment Status\\n1. Create a function `is_ready()` that returns True.",
        "starterCode": "def is_ready():\\n    return ___",
        "solution": "def is_ready():\\n    return True",
        "hint": "Return True.",
        "rubric": "Function returns True."
      },
      {
        "title": "Basic Syntax and Operations",
        "theory": "## Syntax Rules\\nEvery discipline has its syntax. Here we apply standard operations relevant to DevOps Fundamentals.",
        "instructions": "## Task: Basic Math\\n1. Return the sum of a and b.",
        "starterCode": "def add(a, b):\\n    return a ___ b",
        "solution": "def add(a, b):\\n    return a + b",
        "hint": "Use the + operator.",
        "rubric": "Function adds two numbers."
      },
      {
        "title": "Control Structures in DevOps Fundamentals",
        "theory": "## Branching\\nConditional logic dictates how applications respond to different states.",
        "instructions": "## Task: Check State\\n1. Return 'Active' if state is 1, else 'Inactive'.",
        "starterCode": "def check_state(state):\\n    if state == 1:\\n        return '___'\\n    return '___'",
        "solution": "def check_state(state):\\n    if state == 1:\\n        return 'Active'\\n    return 'Inactive'",
        "hint": "Return Active or Inactive.",
        "rubric": "Logic branches correctly."
      },
      {
        "title": "Advanced Memory Management",
        "theory": "## Resource Allocation\\nEfficient memory use is critical, especially when applying DevOps Fundamentals at scale.",
        "instructions": "## Task: Clear Memory\\n1. Set the variable `cache` to an empty dictionary.",
        "starterCode": "cache = {'data': 123}\\ncache = ___",
        "solution": "cache = {'data': 123}\\ncache = {}",
        "hint": "Use {}.",
        "rubric": "Cache is cleared."
      },
      {
        "title": "Object-Oriented Approaches",
        "theory": "## OOP\\nEncapsulating state and behavior within objects helps structure DevOps Fundamentals projects.",
        "instructions": "## Task: Create Class\\n1. Create a class `Module` with a property `name` initialized to 'DevOps Fundamentals'.",
        "starterCode": "class Module:\\n    def __init__(self):\\n        self.name = '___'",
        "solution": "class Module:\\n    def __init__(self):\\n        self.name = 'DevOps Fundamentals'",
        "hint": "Use 'DevOps Fundamentals'.",
        "rubric": "Class encapsulates state."
      },
      {
        "title": "Functional Programming Paradigms",
        "theory": "## Pure Functions\\nFunctional programming avoids side effects. This is increasingly popular in DevOps Fundamentals.",
        "instructions": "## Task: Pure Function\\n1. Write a function `square(x)` that returns x squared.",
        "starterCode": "def square(x):\\n    return x ___ ___",
        "solution": "def square(x):\\n    return x ** 2",
        "hint": "Use ** 2.",
        "rubric": "Pure function implemented."
      },
      {
        "title": "Error Handling and Debugging",
        "theory": "## Resilience\\nHandling exceptions gracefully ensures robustness in DevOps Fundamentals.",
        "instructions": "## Task: Try/Except\\n1. Wrap the division in a try block, catch ZeroDivisionError, and return None.",
        "starterCode": "def safe_div(a, b):\\n    try:\\n        return a / b\\n    ___ ZeroDivisionError:\\n        return ___",
        "solution": "def safe_div(a, b):\\n    try:\\n        return a / b\\n    except ZeroDivisionError:\\n        return None",
        "hint": "Use except and return None.",
        "rubric": "Exceptions caught properly."
      },
      {
        "title": "Advanced Debugging in DevOps Fundamentals",
        "theory": "## Debugging at Scale\\nFinding hard-to-reproduce bugs requires structured methodology.",
        "instructions": "## Task: Debug Setup\\n1. Return True for debugging active.",
        "starterCode": "debug_active = ___",
        "solution": "debug_active = True",
        "hint": "True",
        "rubric": "Debug activated."
      },
      {
        "title": "Profiling DevOps Fundamentals Applications",
        "theory": "## Performance Profiling\\nIdentifying bottlenecks is the first step in optimization.",
        "instructions": "## Task: Profile Scope\\n1. Set `profile_mode` to 'High'.",
        "starterCode": "profile_mode = '___'",
        "solution": "profile_mode = 'High'",
        "hint": "High",
        "rubric": "Profiling set."
      },
      {
        "title": "Memory Leaks and Management",
        "theory": "## Garbage Collection\\nUnderstanding how memory is freed is critical.",
        "instructions": "## Task: GC Status\\n1. Set `gc_enabled` to True.",
        "starterCode": "gc_enabled = ___",
        "solution": "gc_enabled = True",
        "hint": "True",
        "rubric": "GC enabled."
      },
      {
        "title": "Multi-threading Constructs",
        "theory": "## Parallelism\\nUtilizing multiple cores improves execution speed.",
        "instructions": "## Task: Thread Count\\n1. Set `threads` to 8.",
        "starterCode": "threads = ___",
        "solution": "threads = 8",
        "hint": "8",
        "rubric": "Thread count set."
      },
      {
        "title": "Final Project: DevOps Fundamentals",
        "theory": "## Capstone\\nApply all learned concepts to build a comprehensive solution.",
        "instructions": "## Task: Project Initialization\\n1. Set `project_name` to 'DevOps Fundamentals Final'.",
        "starterCode": "project_name = '___'",
        "solution": "project_name = 'DevOps Fundamentals Final'",
        "hint": "DevOps Fundamentals Final",
        "rubric": "Project initialized."
      }
    ]
  },
  "Containers & Infrastructure": {
    "aiRubric": "Check Docker syntax, Docker Compose yaml structure, Terraform HCL logic, and Ansible playbooks.",
    "lessons": [
      {
        "title": "Introduction to Docker & Containerization",
        "theory": "## Dockerfiles\nDefine container images.\n```dockerfile\nFROM node:18\nCOPY . /app\nCMD [\"node\", \"app.js\"]\n```",
        "instructions": "## Task: Docker FROM\nStart a Dockerfile using the `python:3.9-slim` image and set the working directory to `/app`.",
        "starterCode": "___ python:3.9-slim\n___ /app",
        "solution": "FROM python:3.9-slim\nWORKDIR /app",
        "hint": "FROM and WORKDIR",
        "rubric": "FROM and WORKDIR specified."
      },
      {
        "title": "Docker Compose & Multi-Container Apps",
        "theory": "## Docker Compose\nRun multi-container applications via YAML.\n```yaml\nservices:\n  db:\n    image: postgres\n```",
        "instructions": "## Task: Compose Service\nDefine a service named `web` using the `nginx:latest` image mapping port `8080:80`.",
        "starterCode": "services:\n  ___:\n    image: ___\n    ports:\n      - \"___:80\"",
        "solution": "services:\n  web:\n    image: nginx:latest\n    ports:\n      - \"8080:80\"",
        "hint": "web, nginx:latest, and 8080",
        "rubric": "Docker Compose service properly defined."
      },
      {
        "title": "Infrastructure as Code (IaC) Concepts",
        "theory": "## IaC\nManage infrastructure using declarative code. Tools include Terraform, Pulumi, and CloudFormation.",
        "instructions": "## Task: Principles\nDefine the core benefit of IaC by assigning `true` to `isDeclarative`.",
        "starterCode": "const isDeclarative = ___;",
        "solution": "const isDeclarative = true;",
        "hint": "true",
        "rubric": "isDeclarative set to true."
      },
      {
        "title": "Provisioning with Terraform",
        "theory": "## Terraform HCL\nUse HashiCorp Configuration Language to provision resources.\n```hcl\nresource \"aws_s3_bucket\" \"bucket\" {\n  bucket = \"my-bucket\"\n}\n```",
        "instructions": "## Task: AWS EC2 Resource\nDefine an `aws_instance` resource named `web_server` with an ami of `ami-12345`.",
        "starterCode": "resource \"___\" \"___\" {\n  ami = \"___\"\n}",
        "solution": "resource \"aws_instance\" \"web_server\" {\n  ami = \"ami-12345\"\n}",
        "hint": "aws_instance, web_server, ami-12345",
        "rubric": "Terraform resource defined."
      },
      {
        "title": "Configuration Management with Ansible",
        "theory": "## Ansible Playbooks\nAutomate configuration via SSH.\n```yaml\n- hosts: all\n  tasks:\n    - name: Ensure nginx is installed\n      apt: name=nginx state=present\n```",
        "instructions": "## Task: Ansible Task\nWrite a task using the `apt` module to install `git` (state=present).",
        "starterCode": "- hosts: webservers\n  tasks:\n    - name: Install Git\n      ___: name=___ state=___",
        "solution": "- hosts: webservers\n  tasks:\n    - name: Install Git\n      apt: name=git state=present",
        "hint": "apt, git, present",
        "rubric": "Ansible apt task complete."
      },
      {
        "title": "Concurrency and Async Operations",
        "theory": "## Asynchronous Work\\nBlocking operations freeze applications. Async allows overlapping tasks in Containers & Infrastructure.",
        "instructions": "## Task: Async Function\\n1. Define an async function `fetch_data()`.",
        "starterCode": "___ def fetch_data():\\n    return 'Data'",
        "solution": "async def fetch_data():\\n    return 'Data'",
        "hint": "Use async def.",
        "rubric": "Async function defined."
      },
      {
        "title": "Working with Data Structures",
        "theory": "## Data Organization\\nChoosing the right data structure dictates performance.",
        "instructions": "## Task: Use a Set\\n1. Return a set containing the elements 1, 2, 3.",
        "starterCode": "def get_set():\\n    return ___[1, 2, 3]___",
        "solution": "def get_set():\\n    return {1, 2, 3}",
        "hint": "Use {} for sets.",
        "rubric": "Set structure utilized."
      },
      {
        "title": "Network Communication Protocols",
        "theory": "## Connectivity\\nUnderstanding HTTP/TCP is essential for networked components in Containers & Infrastructure.",
        "instructions": "## Task: HTTP Status\\n1. Return 200 for OK.",
        "starterCode": "status_code = ___",
        "solution": "status_code = 200",
        "hint": "200",
        "rubric": "Status code set."
      },
      {
        "title": "File I/O and Storage",
        "theory": "## Persistence\\nSaving data to disk allows state to survive reboots.",
        "instructions": "## Task: Open File\\n1. Write code to open 'data.txt' in read mode.",
        "starterCode": "f = open('data.txt', '___')",
        "solution": "f = open('data.txt', 'r')",
        "hint": "Use 'r'.",
        "rubric": "File opened in correct mode."
      },
      {
        "title": "Security Best Practices",
        "theory": "## Defense\\nProtecting applications from vulnerabilities is non-negotiable.",
        "instructions": "## Task: Hash Length\\n1. Return 64, the length of a SHA-256 hash in hex.",
        "starterCode": "sha256_length = ___",
        "solution": "sha256_length = 64",
        "hint": "64",
        "rubric": "Security constant identified."
      },
      {
        "title": "Performance Optimization Strategies",
        "theory": "## Efficiency\\nOptimizing critical paths improves throughput in Containers & Infrastructure.",
        "instructions": "## Task: Time Complexity\\n1. Return 'O(1)' for constant time complexity.",
        "starterCode": "constant_time = '___'",
        "solution": "constant_time = 'O(1)'",
        "hint": "O(1)",
        "rubric": "Complexity identified."
      },
      {
        "title": "Unit Testing Fundamentals",
        "theory": "## Validation\\nUnit tests verify that individual components work as expected.",
        "instructions": "## Task: Assert True\\n1. Write an assert statement that 1 equals 1.",
        "starterCode": "___ 1 == 1",
        "solution": "assert 1 == 1",
        "hint": "assert",
        "rubric": "Assertion written."
      },
      {
        "title": "Integration Testing",
        "theory": "## System Harmony\\nIntegration tests ensure that components function together.",
        "instructions": "## Task: Integration Status\\n1. Set `integrated` to True.",
        "starterCode": "integrated = ___",
        "solution": "integrated = True",
        "hint": "True",
        "rubric": "Status set."
      }
    ]
  },
  "Orchestration & Observability": {
    "aiRubric": "Check Kubernetes YAML (pods, deployments, services), ArgoCD concepts, and Prometheus/ELK configurations.",
    "lessons": [
      {
        "title": "Introduction to Kubernetes (K8s) Architecture",
        "theory": "## Kubernetes\nOrchestrates containers across clusters.\n```yaml\napiVersion: v1\nkind: Pod\n```",
        "instructions": "## Task: Pod YAML\nComplete the YAML to define a `Pod` with the name `my-app`.",
        "starterCode": "apiVersion: v1\nkind: ___\nmetadata:\n  name: ___\n",
        "solution": "apiVersion: v1\nkind: Pod\nmetadata:\n  name: my-app\n",
        "hint": "Pod and my-app",
        "rubric": "Pod metadata defined correctly."
      },
      {
        "title": "Deploying Pods & Services in Kubernetes",
        "theory": "## Services\nExpose Pods to the network.\n```yaml\nkind: Service\nspec:\n  selector:\n    app: my-app\n```",
        "instructions": "## Task: Service Selector\nMatch the Service selector to the app label `backend` on port `80`.",
        "starterCode": "kind: Service\nspec:\n  ___:\n    app: ___\n  ports:\n    - port: ___",
        "solution": "kind: Service\nspec:\n  selector:\n    app: backend\n  ports:\n    - port: 80",
        "hint": "selector, backend, 80",
        "rubric": "K8s Service selector and port specified."
      },
      {
        "title": "Continuous Deployment (GitOps with ArgoCD)",
        "theory": "## GitOps\nStore the desired state in Git. ArgoCD syncs the cluster to match Git.",
        "instructions": "## Task: Argo Application\nSet the `project` to `default` and the `repoURL` to `https://github.com/my/repo`.",
        "starterCode": "apiVersion: argoproj.io/v1alpha1\nkind: Application\nspec:\n  project: ___\n  source:\n    repoURL: ___\n",
        "solution": "apiVersion: argoproj.io/v1alpha1\nkind: Application\nspec:\n  project: default\n  source:\n    repoURL: https://github.com/my/repo\n",
        "hint": "default and https://github.com/my/repo",
        "rubric": "ArgoCD Application config is correct."
      },
      {
        "title": "Monitoring with Prometheus & Grafana",
        "theory": "## Prometheus\nScrapes metrics from /metrics endpoints.\n```yaml\nscrape_configs:\n  - job_name: 'api'\n```",
        "instructions": "## Task: Scrape Config\nSet the `job_name` to `'prometheus'` and the `static_configs` target to `localhost:9090`.",
        "starterCode": "scrape_configs:\n  - job_name: '___'\n    static_configs:\n      - targets: ['___']",
        "solution": "scrape_configs:\n  - job_name: 'prometheus'\n    static_configs:\n      - targets: ['localhost:9090']",
        "hint": "prometheus and localhost:9090",
        "rubric": "Prometheus scrape target defined."
      },
      {
        "title": "Centralized Logging (ELK Stack)",
        "theory": "## ELK\nElasticsearch, Logstash, Kibana.\n```json\nGET /logs/_search\n{ \"query\": { \"match\": { \"level\": \"error\" } } }\n```",
        "instructions": "## Task: Elastic Query\nWrite the Elasticsearch JSON query to match the `status` field with `500`.",
        "starterCode": "{\n  \"query\": {\n    \"match\": { \"___\": \"___\" }\n  }\n}",
        "solution": "{\n  \"query\": {\n    \"match\": { \"status\": \"500\" }\n  }\n}",
        "hint": "status and 500",
        "rubric": "Elasticsearch query JSON correct."
      },
      {
        "title": "Continuous Integration Setup",
        "theory": "## CI Pipelines\\nCI automatically runs tests when code is pushed.",
        "instructions": "## Task: Pipeline Step\\n1. Create a list with 'build', 'test', 'deploy'.",
        "starterCode": "pipeline = ['___', '___', '___']",
        "solution": "pipeline = ['build', 'test', 'deploy']",
        "hint": "build, test, deploy",
        "rubric": "Pipeline steps defined."
      },
      {
        "title": "Deployment Pipelines",
        "theory": "## Shipping Code\\nDeploying reliably requires automated release pipelines.",
        "instructions": "## Task: Environment\\n1. Set `env` to 'production'.",
        "starterCode": "env = '___'",
        "solution": "env = 'production'",
        "hint": "production",
        "rubric": "Environment set."
      },
      {
        "title": "Logging and Monitoring",
        "theory": "## Observability\\nLogs help diagnose issues in production.",
        "instructions": "## Task: Log Level\\n1. Set `level` to 'ERROR'.",
        "starterCode": "level = '___'",
        "solution": "level = 'ERROR'",
        "hint": "ERROR",
        "rubric": "Log level defined."
      },
      {
        "title": "Design Patterns in Orchestration & Observability",
        "theory": "## Reusable Solutions\\nDesign patterns solve common architectural problems.",
        "instructions": "## Task: Singleton\\n1. Set `pattern` to 'Singleton'.",
        "starterCode": "pattern = '___'",
        "solution": "pattern = 'Singleton'",
        "hint": "Singleton",
        "rubric": "Pattern named."
      },
      {
        "title": "API Integration Strategies",
        "theory": "## Connecting Services\\nAPIs allow different systems to communicate.",
        "instructions": "## Task: JSON Data\\n1. Set `format` to 'JSON'.",
        "starterCode": "format = '___'",
        "solution": "format = 'JSON'",
        "hint": "JSON",
        "rubric": "Format specified."
      },
      {
        "title": "Database Connectivity",
        "theory": "## Data Access\\nConnecting to a DB safely is essential.",
        "instructions": "## Task: Connection String\\n1. Set `conn_str` to 'postgres://localhost'.",
        "starterCode": "conn_str = '___'",
        "solution": "conn_str = 'postgres://localhost'",
        "hint": "postgres://localhost",
        "rubric": "Connection string created."
      },
      {
        "title": "Scaling Applications",
        "theory": "## Horizontal Scaling\\nAdding more instances handles increased load.",
        "instructions": "## Task: Instance Count\\n1. Set `instances` to 3.",
        "starterCode": "instances = ___",
        "solution": "instances = 3",
        "hint": "3",
        "rubric": "Instances scaled."
      },
      {
        "title": "Microservices Architecture",
        "theory": "## Decoupling\\nMicroservices break large apps into independent services.",
        "instructions": "## Task: Service Name\\n1. Set `service` to 'Auth'.",
        "starterCode": "service = '___'",
        "solution": "service = 'Auth'",
        "hint": "Auth",
        "rubric": "Service named."
      },
      {
        "title": "Best Practices and Anti-patterns",
        "theory": "## Writing Clean Code\\nMaintainability ensures the long-term success of Orchestration & Observability projects.",
        "instructions": "## Task: Clean Code\\n1. Set `is_clean` to True.",
        "starterCode": "is_clean = ___",
        "solution": "is_clean = True",
        "hint": "True",
        "rubric": "Clean code enabled."
      }
    ]
  }
}