{
  "Big O Notation": {
    "aiRubric": "Check logic, syntax, and output for Big O Notation.",
    "lessons": [
      {
        "title": "Time Complexity Basics",
        "theory": "## Big O Notation\nBig O describes how an algorithm's runtime grows as input size increases.\n\n```\nO(1)     — Constant    (array access)\nO(log n) — Logarithmic (binary search)\nO(n)     — Linear      (loop through array)\nO(n log n) — Log-linear (merge sort)\nO(n^2)   — Quadratic   (nested loops)\nO(2^n)   — Exponential (recursive fibonacci)\n```\n\nWe always focus on the **worst case** and ignore constants.",
        "instructions": "## Task: Identify Time Complexity\n1. Create functions with different time complexities\n2. Label each with its Big O\n3. Compare them by running with different input sizes",
        "starterCode": "import time\n\n# O(1) - Constant\ndef get_first(arr):\n    return arr[0] if arr else None\n\n# O(n) - Linear\ndef find_max(arr):\n    m = arr[0]\n    for x in arr:\n        if x ___ m: m = x\n    return m\n\n# O(n^2) - Quadratic\ndef has_duplicate(arr):\n    for i in range(len(arr)):\n        for j in range(i+1, len(arr)):\n            if arr[i] ___ arr[j]: return True\n    return False\n\narr = list(range(1000))\nprint(f'First: {get_first(arr)}')\nprint(f'Max: {find_max(arr)}')\nprint(f'Has dup: {has_duplicate(arr)}')",
        "solution": "import time\n\n# O(1) - Constant\ndef get_first(arr):\n    return arr[0] if arr else None\n\n# O(n) - Linear\ndef find_max(arr):\n    m = arr[0]\n    for x in arr:\n        if x > m: m = x\n    return m\n\n# O(n^2) - Quadratic\ndef has_duplicate(arr):\n    for i in range(len(arr)):\n        for j in range(i+1, len(arr)):\n            if arr[i] == arr[j]: return True\n    return False\n\narr = list(range(1000))\nprint(f'First: {get_first(arr)}')\nprint(f'Max: {find_max(arr)}')\nprint(f'Has dup: {has_duplicate(arr)}')",
        "hint": "> for finding max. == for comparing duplicates.",
        "rubric": "Functions implement correct complexities. First: 0, Max: 999, Has dup: False."
      },
      {
        "title": "Space Complexity",
        "theory": "## Space Complexity\nHow much extra memory does your algorithm use?\n\n```python\n# O(1) space - uses fixed extra memory\ndef sum_array(arr):\n    total = 0\n    for x in arr:\n        total += x\n    return total\n\n# O(n) space - creates new array\ndef double_array(arr):\n    result = []\n    for x in arr:\n        result.append(x * 2)\n    return result\n\n# O(n) space - recursive call stack\ndef factorial(n):\n    if n <= 1: return 1\n    return n * factorial(n - 1)\n```",
        "instructions": "## Task: Space-Efficient Reverse\n1. Write `reverse_in_place(arr)` that reverses using O(1) extra space\n2. Write `reverse_new(arr)` that creates a new reversed array O(n) space\n3. Compare both approaches",
        "starterCode": "# O(1) space - swap in place\ndef reverse_in_place(arr):\n    left, right = 0, len(arr) - 1\n    while left ___ right:\n        arr[left], arr[right] = arr[right], arr[left]\n        left ___ 1\n        right ___ 1\n    return arr\n\n# O(n) space - new array\ndef reverse_new(arr):\n    return arr[___]\n\narr1 = [1, 2, 3, 4, 5]\narr2 = arr1.copy()\nprint(f'In-place: {reverse_in_place(arr1)}')\nprint(f'New array: {reverse_new(arr2)}')",
        "solution": "# O(1) space - swap in place\ndef reverse_in_place(arr):\n    left, right = 0, len(arr) - 1\n    while left < right:\n        arr[left], arr[right] = arr[right], arr[left]\n        left += 1\n        right -= 1\n    return arr\n\n# O(n) space - new array\ndef reverse_new(arr):\n    return arr[::-1]\n\narr1 = [1, 2, 3, 4, 5]\narr2 = arr1.copy()\nprint(f'In-place: {reverse_in_place(arr1)}')\nprint(f'New array: {reverse_new(arr2)}')",
        "hint": "left < right to converge. += 1 and -= 1 to move inward. [::-1] reverses.",
        "rubric": "Both produce [5, 4, 3, 2, 1]. In-place uses O(1) space."
      },
      {
        "title": "Comparing Algorithms",
        "theory": "## Choosing the Right Algorithm\n\n| Input Size | O(n) | O(n log n) | O(n^2) |\n|-----------|------|-----------|--------|\n| 10 | 10 | 33 | 100 |\n| 100 | 100 | 664 | 10,000 |\n| 1,000 | 1,000 | 9,966 | 1,000,000 |\n| 1,000,000 | 1M | 20M | 1 TRILLION |\n\nAt scale, algorithm choice matters enormously!",
        "instructions": "## Task: Benchmark Comparison\n1. Implement linear search O(n) and binary search O(log n)\n2. Time both on a sorted array of 100,000 elements\n3. Print the time difference",
        "starterCode": "import time\n\ndef linear_search(arr, target):\n    for i in range(len(arr)):\n        if arr[i] == target:\n            return i\n    return -1\n\ndef binary_search(arr, target):\n    low, high = 0, len(arr) - 1\n    while low ___ high:\n        mid = (low + high) // 2\n        if arr[mid] == target:\n            return mid\n        elif arr[mid] ___ target:\n            low = mid + 1\n        else:\n            high = mid - 1\n    return -1\n\narr = list(range(100000))\ntarget = 99999\n\nstart = time.time()\nlinear_search(arr, target)\nlinear_time = time.time() - start\n\nstart = time.time()\nbinary_search(arr, target)\nbinary_time = time.time() - start\n\nprint(f'Linear: {linear_time:.6f}s')\nprint(f'Binary: {binary_time:.6f}s')\nprint(f'Binary is {linear_time/max(binary_time,0.000001):.0f}x faster')",
        "solution": "import time\n\ndef linear_search(arr, target):\n    for i in range(len(arr)):\n        if arr[i] == target:\n            return i\n    return -1\n\ndef binary_search(arr, target):\n    low, high = 0, len(arr) - 1\n    while low <= high:\n        mid = (low + high) // 2\n        if arr[mid] == target:\n            return mid\n        elif arr[mid] < target:\n            low = mid + 1\n        else:\n            high = mid - 1\n    return -1\n\narr = list(range(100000))\ntarget = 99999\n\nstart = time.time()\nlinear_search(arr, target)\nlinear_time = time.time() - start\n\nstart = time.time()\nbinary_search(arr, target)\nbinary_time = time.time() - start\n\nprint(f'Linear: {linear_time:.6f}s')\nprint(f'Binary: {binary_time:.6f}s')\nprint(f'Binary is {linear_time/max(binary_time,0.000001):.0f}x faster')",
        "hint": "<= for while condition. < target means search right half (low = mid + 1).",
        "rubric": "Both find the target. Binary search is significantly faster."
      },
      {
        "title": "Best/Average/Worst Case",
        "theory": "## Cases Matter\n\n```python\ndef linear_search(arr, target):\n    for i, x in enumerate(arr):\n        if x == target:\n            return i\n    return -1\n```\n\n- **Best case:** O(1) — target is first element\n- **Average case:** O(n/2) = O(n) — target is in the middle\n- **Worst case:** O(n) — target is last or not present\n\nWe usually talk about **worst case** unless specified.",
        "instructions": "## Task: Analyze Cases\n1. Create a search function that counts comparisons\n2. Test with best case (first element), average (middle), worst (last)\n3. Print the number of comparisons for each",
        "starterCode": "def search_with_count(arr, target):\n    comparisons = 0\n    for i in range(len(arr)):\n        comparisons ___ 1\n        if arr[i] == target:\n            return i, comparisons\n    return -1, comparisons\n\narr = list(range(1000))\n\nbest_idx, best_comp = search_with_count(arr, ___)\navg_idx, avg_comp = search_with_count(arr, ___)\nworst_idx, worst_comp = search_with_count(arr, ___)\n\nprint(f'Best case: {best_comp} comparisons')\nprint(f'Average case: {avg_comp} comparisons')\nprint(f'Worst case: {worst_comp} comparisons')",
        "solution": "def search_with_count(arr, target):\n    comparisons = 0\n    for i in range(len(arr)):\n        comparisons += 1\n        if arr[i] == target:\n            return i, comparisons\n    return -1, comparisons\n\narr = list(range(1000))\n\nbest_idx, best_comp = search_with_count(arr, 0)\navg_idx, avg_comp = search_with_count(arr, 500)\nworst_idx, worst_comp = search_with_count(arr, 999)\n\nprint(f'Best case: {best_comp} comparisons')\nprint(f'Average case: {avg_comp} comparisons')\nprint(f'Worst case: {worst_comp} comparisons')",
        "hint": "+= 1 counts. 0 for best (first), 500 for average, 999 for worst (last).",
        "rubric": "Best: 1 comparison. Average: 501. Worst: 1000."
      },
      {
        "title": "Amortized Analysis",
        "theory": "## Amortized Time\nSome operations are expensive occasionally but cheap on average.\n\n```python\n# Python list.append() is O(1) amortized\n# Usually O(1), but occasionally O(n) when resizing\narr = []\nfor i in range(1000000):\n    arr.append(i)  # Total time: O(n), so each append is O(1) amortized\n```\n\nAmortized = total cost / number of operations",
        "instructions": "## Task: Dynamic Array\n1. Implement a simplified dynamic array that doubles capacity when full\n2. Track the number of copy operations during resizing\n3. Show that amortized cost per insert is O(1)",
        "starterCode": "class DynamicArray:\n    def __init__(self):\n        self.data = [None] * 2\n        self.size = 0\n        self.capacity = 2\n        self.total_copies = 0\n    \n    def append(self, value):\n        if self.size == self.capacity:\n            self._resize()\n        self.data[self.___] = value\n        self.size ___ 1\n    \n    def _resize(self):\n        new_cap = self.capacity * ___\n        new_data = [None] * new_cap\n        for i in range(self.size):\n            new_data[i] = self.data[i]\n            self.total_copies += 1\n        self.data = new_data\n        self.capacity = new_cap\n\narr = DynamicArray()\nfor i in range(100):\n    arr.append(i)\n\nprint(f'Size: {arr.size}')\nprint(f'Capacity: {arr.capacity}')\nprint(f'Total copies: {arr.total_copies}')\nprint(f'Amortized copies per insert: {arr.total_copies / arr.size:.2f}')",
        "solution": "class DynamicArray:\n    def __init__(self):\n        self.data = [None] * 2\n        self.size = 0\n        self.capacity = 2\n        self.total_copies = 0\n    \n    def append(self, value):\n        if self.size == self.capacity:\n            self._resize()\n        self.data[self.size] = value\n        self.size += 1\n    \n    def _resize(self):\n        new_cap = self.capacity * 2\n        new_data = [None] * new_cap\n        for i in range(self.size):\n            new_data[i] = self.data[i]\n            self.total_copies += 1\n        self.data = new_data\n        self.capacity = new_cap\n\narr = DynamicArray()\nfor i in range(100):\n    arr.append(i)\n\nprint(f'Size: {arr.size}')\nprint(f'Capacity: {arr.capacity}')\nprint(f'Total copies: {arr.total_copies}')\nprint(f'Amortized copies per insert: {arr.total_copies / arr.size:.2f}')",
        "hint": "self.size for next empty index. += 1 to grow. * 2 to double capacity.",
        "rubric": "Array grows dynamically. Amortized copies per insert is close to 1."
      }
    ]
  },
  "Arrays & Strings": {
    "aiRubric": "Check logic, syntax, and output for Arrays & Strings.",
    "lessons": [
      {
        "title": "C Arrays",
        "theory": "## Arrays in C\nArrays store multiple values of the same type.\n\n```c\nint scores[5] = {90, 85, 78, 92, 88};\nfloat temps[3] = {36.5, 37.0, 36.8};\n\n// Access elements (0-indexed)\nprintf(\"%d\n\", scores[0]);  // 90\nscores[2] = 80;              // Modify\n\n// Array size\nint size = sizeof(scores) / sizeof(scores[0]);  // 5\n```",
        "instructions": "## Task: Array Operations\n1. Create an array of 5 test scores\n2. Calculate and print the average\n3. Find and print the highest score",
        "starterCode": "#include <stdio.h>\n\nint main() {\n    int scores[] = {85, 92, 78, 95, 88};\n    int size = sizeof(scores) / sizeof(scores[___]);\n    int sum = 0, max = scores[0];\n    \n    for (int i = 0; i < ___; i++) {\n        sum ___ scores[i];\n        if (scores[i] ___ max)\n            max = scores[i];\n    }\n    \n    printf(\"Average: %.1f\n\", (float)sum / size);\n    printf(\"Highest: %d\n\", max);\n    return 0;\n}",
        "solution": "#include <stdio.h>\n\nint main() {\n    int scores[] = {85, 92, 78, 95, 88};\n    int size = sizeof(scores) / sizeof(scores[0]);\n    int sum = 0, max = scores[0];\n    \n    for (int i = 0; i < size; i++) {\n        sum += scores[i];\n        if (scores[i] > max)\n            max = scores[i];\n    }\n    \n    printf(\"Average: %.1f\n\", (float)sum / size);\n    printf(\"Highest: %d\n\", max);\n    return 0;\n}",
        "hint": "sizeof(arr)/sizeof(arr[0]) gets length. += to sum. > to find max.",
        "rubric": "Average calculated correctly. Max is 95."
      },
      {
        "title": "String Functions",
        "theory": "## Strings in C\nStrings are character arrays ending with `\\0` (null terminator).\n\n```c\n#include <string.h>\n\nchar name[] = \"Alice\";\nprintf(\"%lu\n\", strlen(name));       // 5\n\nchar dest[20];\nstrcpy(dest, \"Hello\");               // Copy\nstrcat(dest, \" World\");              // Concatenate\nprintf(\"%d\n\", strcmp(\"abc\", \"def\")); // Compare (<0)\n```",
        "instructions": "## Task: String Utilities\n1. Create a string and find its length\n2. Copy it to another string\n3. Concatenate two strings\n4. Compare two strings",
        "starterCode": "#include <stdio.h>\n#include <string.h>\n\nint main() {\n    char greeting[50] = \"Hello\";\n    char name[] = \"Mabel\";\n    char full[50];\n    \n    printf(\"Length: %lu\n\", ___(greeting));\n    \n    ___(full, greeting);     // Copy greeting to full\n    ___(full, \" \");          // Add space\n    ___(full, name);          // Add name\n    \n    printf(\"Full: %s\n\", full);\n    printf(\"Equal? %d\n\", ___(greeting, \"Hello\") == 0);\n    return 0;\n}",
        "solution": "#include <stdio.h>\n#include <string.h>\n\nint main() {\n    char greeting[50] = \"Hello\";\n    char name[] = \"Mabel\";\n    char full[50];\n    \n    printf(\"Length: %lu\n\", strlen(greeting));\n    \n    strcpy(full, greeting);     // Copy greeting to full\n    strcat(full, \" \");          // Add space\n    strcat(full, name);          // Add name\n    \n    printf(\"Full: %s\n\", full);\n    printf(\"Equal? %d\n\", strcmp(greeting, \"Hello\") == 0);\n    return 0;\n}",
        "hint": "strlen for length. strcpy copies. strcat concatenates. strcmp compares (0 = equal).",
        "rubric": "Length is 5. Full is 'Hello Mabel'. Comparison returns true (1)."
      },
      {
        "title": "2D Arrays",
        "theory": "## Multidimensional Arrays\n\n```c\nint matrix[3][3] = {\n    {1, 2, 3},\n    {4, 5, 6},\n    {7, 8, 9}\n};\n\n// Access: matrix[row][col]\nprintf(\"%d\n\", matrix[1][2]);  // 6\n\n// Iterate\nfor (int i = 0; i < 3; i++) {\n    for (int j = 0; j < 3; j++) {\n        printf(\"%d \", matrix[i][j]);\n    }\n    printf(\"\n\");\n}\n```",
        "instructions": "## Task: Matrix Sum\n1. Create a 3x3 matrix\n2. Calculate and print the sum of all elements\n3. Calculate and print the sum of the main diagonal",
        "starterCode": "#include <stdio.h>\n\nint main() {\n    int matrix[3][3] = {\n        {1, 2, 3},\n        {4, 5, 6},\n        {7, 8, 9}\n    };\n    int total = 0, diagonal = 0;\n    \n    for (int i = 0; i < 3; i++) {\n        for (int j = 0; j < 3; j++) {\n            total ___ matrix[i][j];\n        }\n        diagonal ___ matrix[i][___];\n    }\n    \n    printf(\"Total sum: %d\n\", total);\n    printf(\"Diagonal sum: %d\n\", diagonal);\n    return 0;\n}",
        "solution": "#include <stdio.h>\n\nint main() {\n    int matrix[3][3] = {\n        {1, 2, 3},\n        {4, 5, 6},\n        {7, 8, 9}\n    };\n    int total = 0, diagonal = 0;\n    \n    for (int i = 0; i < 3; i++) {\n        for (int j = 0; j < 3; j++) {\n            total += matrix[i][j];\n        }\n        diagonal += matrix[i][i];\n    }\n    \n    printf(\"Total sum: %d\n\", total);\n    printf(\"Diagonal sum: %d\n\", diagonal);\n    return 0;\n}",
        "hint": "+= to accumulate. matrix[i][i] gives diagonal elements (0,0), (1,1), (2,2).",
        "rubric": "Total sum is 45. Diagonal sum is 15 (1+5+9)."
      },
      {
        "title": "String Manipulation",
        "theory": "## Manual String Operations\nSince C doesn't have built-in string methods like Python, you often write your own.\n\n```c\n// Convert to uppercase manually\nvoid to_upper(char *str) {\n    while (*str) {\n        if (*str >= 'a' && *str <= 'z')\n            *str -= 32;  // ASCII difference\n        str++;\n    }\n}\n```",
        "instructions": "## Task: Custom String Functions\n1. Write `int count_vowels(char *str)` that counts vowels\n2. Write `void reverse_string(char *str)` that reverses in-place\n3. Test both",
        "starterCode": "#include <stdio.h>\n#include <string.h>\n\nint count_vowels(char *str) {\n    int count = 0;\n    while (*str) {\n        char c = *str;\n        if (c=='a'||c=='e'||c=='i'||c=='o'||c=='u'||\n            c=='A'||c=='E'||c=='I'||c=='O'||c=='U')\n            count___;\n        str___;\n    }\n    return count;\n}\n\nvoid reverse_string(char *str) {\n    int len = strlen(str);\n    for (int i = 0; i < len/2; i++) {\n        char temp = str[i];\n        str[i] = str[len-1-___];\n        str[len-1-i] = ___;\n    }\n}\n\nint main() {\n    char text[] = \"Hello World\";\n    printf(\"Vowels: %d\n\", count_vowels(text));\n    reverse_string(text);\n    printf(\"Reversed: %s\n\", text);\n    return 0;\n}",
        "solution": "#include <stdio.h>\n#include <string.h>\n\nint count_vowels(char *str) {\n    int count = 0;\n    while (*str) {\n        char c = *str;\n        if (c=='a'||c=='e'||c=='i'||c=='o'||c=='u'||\n            c=='A'||c=='E'||c=='I'||c=='O'||c=='U')\n            count++;\n        str++;\n    }\n    return count;\n}\n\nvoid reverse_string(char *str) {\n    int len = strlen(str);\n    for (int i = 0; i < len/2; i++) {\n        char temp = str[i];\n        str[i] = str[len-1-i];\n        str[len-1-i] = temp;\n    }\n}\n\nint main() {\n    char text[] = \"Hello World\";\n    printf(\"Vowels: %d\n\", count_vowels(text));\n    reverse_string(text);\n    printf(\"Reversed: %s\n\", text);\n    return 0;\n}",
        "hint": "++ to increment count and pointer. Swap str[i] with str[len-1-i].",
        "rubric": "Vowels: 3 (e, o, o). Reversed: dlroW olleH."
      },
      {
        "title": "Command Line Arguments",
        "theory": "## argc and argv\n\n```c\nint main(int argc, char *argv[]) {\n    printf(\"Arguments: %d\n\", argc);\n    for (int i = 0; i < argc; i++) {\n        printf(\"argv[%d] = %s\n\", i, argv[i]);\n    }\n    return 0;\n}\n```\n\n- `argc` = argument count\n- `argv[0]` = program name\n- `argv[1]` = first argument, etc.",
        "instructions": "## Task: Argument Parser\n1. Simulate command-line argument parsing\n2. Parse key=value pairs from a string array\n3. Print each key and value",
        "starterCode": "#include <stdio.h>\n#include <string.h>\n\nint main() {\n    // Simulated arguments\n    char *args[] = {\"./app\", \"--name=Mabel\", \"--port=3000\", \"--debug=true\"};\n    int argc = 4;\n    \n    for (int i = 1; i < ___; i++) {\n        char *eq = strchr(args[i], '=');\n        if (eq != ___) {\n            int key_len = eq - args[i];\n            printf(\"Key: %.*s, Value: %s\n\", key_len, args[i], eq + 1);\n        }\n    }\n    return 0;\n}",
        "solution": "#include <stdio.h>\n#include <string.h>\n\nint main() {\n    // Simulated arguments\n    char *args[] = {\"./app\", \"--name=Mabel\", \"--port=3000\", \"--debug=true\"};\n    int argc = 4;\n    \n    for (int i = 1; i < argc; i++) {\n        char *eq = strchr(args[i], '=');\n        if (eq != NULL) {\n            int key_len = eq - args[i];\n            printf(\"Key: %.*s, Value: %s\n\", key_len, args[i], eq + 1);\n        }\n    }\n    return 0;\n}",
        "hint": "strchr finds '=' character. eq+1 points to value after '='. eq-args[i] gives key length.",
        "rubric": "All 3 key-value pairs parsed correctly."
      }
    ]
  },
  "Linked Lists": {
    "aiRubric": "Check logic, syntax, and output for Linked Lists.",
    "lessons": [
      {
        "title": "Singly Linked List",
        "theory": "## Linked Lists\nA linked list stores elements in nodes, where each node points to the next.\n\n```python\nclass Node:\n    def __init__(self, data):\n        self.data = data\n        self.next = None\n\nclass LinkedList:\n    def __init__(self):\n        self.head = None\n```\n\nUnlike arrays, linked lists can grow without resizing and insert/delete in O(1).",
        "instructions": "## Task: Build a Linked List\n1. Create Node and LinkedList classes\n2. Implement `append(data)`, `display()`, and `length()`\n3. Test with 5 values",
        "starterCode": "class Node:\n    def __init__(self, data):\n        self.data = data\n        self.next = ___\n\nclass LinkedList:\n    def __init__(self):\n        self.head = None\n    \n    def append(self, data):\n        new_node = Node(data)\n        if self.head is None:\n            self.head = new_node\n            return\n        current = self.head\n        while current.___ is not None:\n            current = current.next\n        current.next = ___\n    \n    def display(self):\n        items = []\n        current = self.head\n        while current:\n            items.append(str(current.data))\n            current = current.next\n        print(' -> '.join(items))\n    \n    def length(self):\n        count = 0\n        current = self.head\n        while current:\n            count += 1\n            current = current.___\n        return count\n\nll = LinkedList()\nfor v in [10, 20, 30, 40, 50]:\n    ll.append(v)\nll.display()\nprint(f'Length: {ll.length()}')",
        "solution": "class Node:\n    def __init__(self, data):\n        self.data = data\n        self.next = None\n\nclass LinkedList:\n    def __init__(self):\n        self.head = None\n    \n    def append(self, data):\n        new_node = Node(data)\n        if self.head is None:\n            self.head = new_node\n            return\n        current = self.head\n        while current.next is not None:\n            current = current.next\n        current.next = new_node\n    \n    def display(self):\n        items = []\n        current = self.head\n        while current:\n            items.append(str(current.data))\n            current = current.next\n        print(' -> '.join(items))\n    \n    def length(self):\n        count = 0\n        current = self.head\n        while current:\n            count += 1\n            current = current.next\n        return count\n\nll = LinkedList()\nfor v in [10, 20, 30, 40, 50]:\n    ll.append(v)\nll.display()\nprint(f'Length: {ll.length()}')",
        "hint": "None for empty next. Traverse with while current.next. Set current.next = new_node.",
        "rubric": "Display: 10 -> 20 -> 30 -> 40 -> 50. Length: 5."
      },
      {
        "title": "Insert & Delete",
        "theory": "## Linked List Operations\n\n```python\n# Insert at beginning: O(1)\ndef prepend(self, data):\n    new_node = Node(data)\n    new_node.next = self.head\n    self.head = new_node\n\n# Delete by value: O(n)\ndef delete(self, data):\n    if self.head and self.head.data == data:\n        self.head = self.head.next\n        return\n    current = self.head\n    while current.next:\n        if current.next.data == data:\n            current.next = current.next.next\n            return\n        current = current.next\n```",
        "instructions": "## Task: Full Linked List Operations\n1. Add `prepend(data)` to insert at the beginning\n2. Add `delete(data)` to remove by value\n3. Add `insert_at(index, data)` to insert at a position",
        "starterCode": "class Node:\n    def __init__(self, data):\n        self.data = data\n        self.next = None\n\nclass LinkedList:\n    def __init__(self):\n        self.head = None\n    \n    def append(self, data):\n        node = Node(data)\n        if not self.head: self.head = node; return\n        cur = self.head\n        while cur.next: cur = cur.next\n        cur.next = node\n    \n    def prepend(self, data):\n        node = Node(data)\n        node.next = self.___\n        self.head = ___\n    \n    def delete(self, data):\n        if self.head and self.head.data == data:\n            self.head = self.head.___\n            return\n        cur = self.head\n        while cur and cur.next:\n            if cur.next.data == data:\n                cur.next = cur.next.___\n                return\n            cur = cur.next\n    \n    def display(self):\n        items, cur = [], self.head\n        while cur: items.append(str(cur.data)); cur = cur.next\n        print(' -> '.join(items) if items else 'Empty')\n\nll = LinkedList()\nfor v in [20, 30, 40]: ll.append(v)\nll.prepend(10)\nll.display()\nll.delete(30)\nll.display()",
        "solution": "class Node:\n    def __init__(self, data):\n        self.data = data\n        self.next = None\n\nclass LinkedList:\n    def __init__(self):\n        self.head = None\n    \n    def append(self, data):\n        node = Node(data)\n        if not self.head: self.head = node; return\n        cur = self.head\n        while cur.next: cur = cur.next\n        cur.next = node\n    \n    def prepend(self, data):\n        node = Node(data)\n        node.next = self.head\n        self.head = node\n    \n    def delete(self, data):\n        if self.head and self.head.data == data:\n            self.head = self.head.next\n            return\n        cur = self.head\n        while cur and cur.next:\n            if cur.next.data == data:\n                cur.next = cur.next.next\n                return\n            cur = cur.next\n    \n    def display(self):\n        items, cur = [], self.head\n        while cur: items.append(str(cur.data)); cur = cur.next\n        print(' -> '.join(items) if items else 'Empty')\n\nll = LinkedList()\nfor v in [20, 30, 40]: ll.append(v)\nll.prepend(10)\nll.display()\nll.delete(30)\nll.display()",
        "hint": "Prepend: point new node to old head, update head. Delete: skip the node.",
        "rubric": "After prepend: 10->20->30->40. After delete 30: 10->20->40."
      },
      {
        "title": "Reverse a Linked List",
        "theory": "## Classic Interview Question\nReversing a linked list is one of the most common interview questions.\n\n```\nBefore: 1 -> 2 -> 3 -> 4 -> None\nAfter:  4 -> 3 -> 2 -> 1 -> None\n```\n\nUse three pointers: `prev`, `current`, `next`.",
        "instructions": "## Task: Reverse Linked List\n1. Implement `reverse()` method using iterative approach\n2. Use three pointers: prev, current, next_node\n3. Test by displaying before and after",
        "starterCode": "class Node:\n    def __init__(self, data):\n        self.data = data\n        self.next = None\n\nclass LinkedList:\n    def __init__(self):\n        self.head = None\n    \n    def append(self, data):\n        node = Node(data)\n        if not self.head: self.head = node; return\n        cur = self.head\n        while cur.next: cur = cur.next\n        cur.next = node\n    \n    def reverse(self):\n        prev = ___\n        current = self.head\n        while current:\n            next_node = current.___\n            current.next = ___\n            prev = ___\n            current = next_node\n        self.head = ___\n    \n    def display(self):\n        items, cur = [], self.head\n        while cur: items.append(str(cur.data)); cur = cur.next\n        print(' -> '.join(items))\n\nll = LinkedList()\nfor v in [1, 2, 3, 4, 5]: ll.append(v)\nprint('Before:'); ll.display()\nll.reverse()\nprint('After:'); ll.display()",
        "solution": "class Node:\n    def __init__(self, data):\n        self.data = data\n        self.next = None\n\nclass LinkedList:\n    def __init__(self):\n        self.head = None\n    \n    def append(self, data):\n        node = Node(data)\n        if not self.head: self.head = node; return\n        cur = self.head\n        while cur.next: cur = cur.next\n        cur.next = node\n    \n    def reverse(self):\n        prev = None\n        current = self.head\n        while current:\n            next_node = current.next\n            current.next = prev\n            prev = current\n            current = next_node\n        self.head = prev\n    \n    def display(self):\n        items, cur = [], self.head\n        while cur: items.append(str(cur.data)); cur = cur.next\n        print(' -> '.join(items))\n\nll = LinkedList()\nfor v in [1, 2, 3, 4, 5]: ll.append(v)\nprint('Before:'); ll.display()\nll.reverse()\nprint('After:'); ll.display()",
        "hint": "prev starts None. Save next, point current back to prev, advance both.",
        "rubric": "Before: 1->2->3->4->5. After: 5->4->3->2->1."
      },
      {
        "title": "Detect Cycle",
        "theory": "## Floyd's Cycle Detection\nUse two pointers (slow and fast) to detect cycles.\n\n```\nIf fast catches up to slow, there's a cycle!\n\nSlow moves 1 step at a time.\nFast moves 2 steps at a time.\n```\n\nThis is called the **tortoise and hare** algorithm.",
        "instructions": "## Task: Cycle Detection\n1. Create a linked list\n2. Implement `has_cycle()` using Floyd's algorithm\n3. Test with a normal list and one with a cycle",
        "starterCode": "class Node:\n    def __init__(self, data):\n        self.data = data\n        self.next = None\n\ndef has_cycle(head):\n    slow = head\n    fast = head\n    while fast and fast.next:\n        slow = slow.___\n        fast = fast.next.___\n        if slow ___ fast:\n            return True\n    return False\n\n# No cycle\na, b, c = Node(1), Node(2), Node(3)\na.next = b; b.next = c\nprint(f'Has cycle: {has_cycle(a)}')\n\n# With cycle\nx, y, z = Node(1), Node(2), Node(3)\nx.next = y; y.next = z; z.next = x  # Cycle!\nprint(f'Has cycle: {has_cycle(x)}')",
        "solution": "class Node:\n    def __init__(self, data):\n        self.data = data\n        self.next = None\n\ndef has_cycle(head):\n    slow = head\n    fast = head\n    while fast and fast.next:\n        slow = slow.next\n        fast = fast.next.next\n        if slow == fast:\n            return True\n    return False\n\n# No cycle\na, b, c = Node(1), Node(2), Node(3)\na.next = b; b.next = c\nprint(f'Has cycle: {has_cycle(a)}')\n\n# With cycle\nx, y, z = Node(1), Node(2), Node(3)\nx.next = y; y.next = z; z.next = x  # Cycle!\nprint(f'Has cycle: {has_cycle(x)}')",
        "hint": "slow.next moves 1 step. fast.next.next moves 2 steps. == to check if they meet.",
        "rubric": "No cycle: False. With cycle: True. Floyd's algorithm implemented."
      },
      {
        "title": "Merge Two Sorted Lists",
        "theory": "## Merging Sorted Lists\nAnother classic interview question: merge two sorted linked lists into one.\n\n```\nList A: 1 -> 3 -> 5\nList B: 2 -> 4 -> 6\nResult: 1 -> 2 -> 3 -> 4 -> 5 -> 6\n```\n\nCompare heads, take the smaller one, advance that pointer.",
        "instructions": "## Task: Merge Sorted Lists\n1. Create two sorted linked lists\n2. Merge them into a single sorted list\n3. Display the result",
        "starterCode": "class Node:\n    def __init__(self, data):\n        self.data = data\n        self.next = None\n\ndef merge_sorted(h1, h2):\n    dummy = Node(0)\n    current = dummy\n    while h1 and h2:\n        if h1.data ___ h2.data:\n            current.next = ___\n            h1 = h1.next\n        else:\n            current.next = ___\n            h2 = h2.next\n        current = current.next\n    current.next = h1 if h1 else h2\n    return dummy.next\n\ndef display(head):\n    items = []\n    while head: items.append(str(head.data)); head = head.next\n    print(' -> '.join(items))\n\n# Create sorted lists\na1, a2, a3 = Node(1), Node(3), Node(5)\na1.next = a2; a2.next = a3\nb1, b2, b3 = Node(2), Node(4), Node(6)\nb1.next = b2; b2.next = b3\n\nresult = merge_sorted(a1, b1)\ndisplay(result)",
        "solution": "class Node:\n    def __init__(self, data):\n        self.data = data\n        self.next = None\n\ndef merge_sorted(h1, h2):\n    dummy = Node(0)\n    current = dummy\n    while h1 and h2:\n        if h1.data <= h2.data:\n            current.next = h1\n            h1 = h1.next\n        else:\n            current.next = h2\n            h2 = h2.next\n        current = current.next\n    current.next = h1 if h1 else h2\n    return dummy.next\n\ndef display(head):\n    items = []\n    while head: items.append(str(head.data)); head = head.next\n    print(' -> '.join(items))\n\n# Create sorted lists\na1, a2, a3 = Node(1), Node(3), Node(5)\na1.next = a2; a2.next = a3\nb1, b2, b3 = Node(2), Node(4), Node(6)\nb1.next = b2; b2.next = b3\n\nresult = merge_sorted(a1, b1)\ndisplay(result)",
        "hint": "<= takes the smaller. Attach the remaining list at the end.",
        "rubric": "Output: 1 -> 2 -> 3 -> 4 -> 5 -> 6. Sorted correctly."
      }
    ]
  },
  "Stacks & Queues": {
    "aiRubric": "Check logic, syntax, and output for Stacks & Queues.",
    "lessons": [
      {
        "title": "Stack (LIFO)",
        "theory": "## Last In, First Out\nA stack is like a stack of plates. You add to the top (push) and remove from the top (pop).\n\nUse cases:\n- Function call stack\n- Undo mechanisms\n- Browser history (Back button)\n\nIn Python, a standard `list` is a perfect stack (using `.append()` and `.pop()`).",
        "instructions": "## Task: Balanced Parentheses\n1. Use a stack to check if a string of parentheses is balanced\n2. Push on `(`, pop on `)`\n3. If you try to pop an empty stack, or if the stack isn't empty at the end, it's unbalanced",
        "starterCode": "def is_balanced(s):\n    stack = []\n    for char in s:\n        if char == '(':\n            stack.___(char)\n        elif char == ')':\n            if not stack: # Empty stack!\n                return ___\n            stack.___()\n    return len(___) == 0\n\nprint(\"(())\", is_balanced(\"(())\"))\nprint(\"(()\", is_balanced(\"(()\"))\nprint(\")(\", is_balanced(\")(\"))",
        "solution": "def is_balanced(s):\n    stack = []\n    for char in s:\n        if char == '(':\n            stack.append(char)\n        elif char == ')':\n            if not stack: # Empty stack!\n                return False\n            stack.pop()\n    return len(stack) == 0\n\nprint(\"(())\", is_balanced(\"(())\"))\nprint(\"(()\", is_balanced(\"(()\"))\nprint(\")(\", is_balanced(\")(\"))",
        "hint": "append() to push. pop() to remove. Return False if stack empty on ')'. Check len(stack) at end.",
        "rubric": "(()) is True. (() and )( are False."
      },
      {
        "title": "Queue (FIFO)",
        "theory": "## First In, First Out\nA queue is like a line at a store. The first person in line is the first one served.\n\nUse cases:\n- Print spooler\n- Breadth-First Search (BFS)\n- Task processing queues\n\nIn Python, use `collections.deque` for O(1) pops from the front. Standard lists are O(n) to pop from the front.",
        "instructions": "## Task: Hot Potato Simulation\n1. Use a queue (standard list for simplicity here) to simulate hot potato\n2. Dequeue from front, enqueue to back `num` times\n3. The person at the front is eliminated. Repeat until 1 left.",
        "starterCode": "def hot_potato(names, num):\n    queue = names.copy()\n    \n    while len(queue) > 1:\n        for _ in range(num):\n            # Move person from front to back\n            person = queue.pop(___)\n            queue.___(person)\n        # Eliminate person at front\n        eliminated = queue.___(0)\n        print(f\"Eliminated: {eliminated}\")\n        \n    return queue[0]\n\nwinner = hot_potato([\"Alice\", \"Bob\", \"Charlie\", \"David\", \"Eve\"], 3)\nprint(f\"Winner is: {winner}\")",
        "solution": "def hot_potato(names, num):\n    queue = names.copy()\n    \n    while len(queue) > 1:\n        for _ in range(num):\n            # Move person from front to back\n            person = queue.pop(0)\n            queue.append(person)\n        # Eliminate person at front\n        eliminated = queue.pop(0)\n        print(f\"Eliminated: {eliminated}\")\n        \n    return queue[0]\n\nwinner = hot_potato([\"Alice\", \"Bob\", \"Charlie\", \"David\", \"Eve\"], 3)\nprint(f\"Winner is: {winner}\")",
        "hint": "pop(0) removes from front. append() adds to back.",
        "rubric": "People are eliminated correctly until only 1 winner remains."
      }
    ]
  },
  "Trees & Graphs": {
    "aiRubric": "Check logic, syntax, and output for Trees & Graphs.",
    "lessons": [
      {
        "title": "Binary Trees",
        "theory": "## Hierarchical Data\nA tree consists of nodes with parent-child relationships. A **Binary Tree** means each node has at most 2 children (left and right).\n\n```python\nclass TreeNode:\n    def __init__(self, val):\n        self.val = val\n        self.left = None\n        self.right = None\n```\n\nThe top node is the **root**. Nodes with no children are **leaves**.",
        "instructions": "## Task: Build a Binary Tree\n1. Create a TreeNode class\n2. Create a root node with value 10\n3. Add left child 5, right child 15\n4. Add left child 2 to node 5",
        "starterCode": "class TreeNode:\n    def __init__(self, val):\n        self.val = val\n        self.left = None\n        self.right = None\n\nroot = TreeNode(___)\nroot.left = TreeNode(___)\nroot.right = TreeNode(___)\nroot.left.left = TreeNode(___)\n\nprint(f\"Root: {root.val}\")\nprint(f\"Left child: {root.left.val}\")\nprint(f\"Right child: {root.right.val}\")\nprint(f\"Deepest left: {root.left.left.val}\")",
        "solution": "class TreeNode:\n    def __init__(self, val):\n        self.val = val\n        self.left = None\n        self.right = None\n\nroot = TreeNode(10)\nroot.left = TreeNode(5)\nroot.right = TreeNode(15)\nroot.left.left = TreeNode(2)\n\nprint(f\"Root: {root.val}\")\nprint(f\"Left child: {root.left.val}\")\nprint(f\"Right child: {root.right.val}\")\nprint(f\"Deepest left: {root.left.left.val}\")",
        "hint": "Assign TreeNode objects to .left and .right properties.",
        "rubric": "Tree built with values 10, 5, 15, and 2 in the correct places."
      },
      {
        "title": "Tree Traversal",
        "theory": "## Visiting Every Node\nHow do you print every node in a tree? Recursion is the easiest way!\n\n- **Inorder**: Left, Node, Right (prints sorted in BSTs)\n- **Preorder**: Node, Left, Right\n- **Postorder**: Left, Right, Node\n\n```python\ndef inorder(node):\n    if not node: return\n    inorder(node.left)\n    print(node.val)\n    inorder(node.right)\n```",
        "instructions": "## Task: Inorder Traversal\n1. Write a recursive `inorder(node)` function\n2. It should append values to a global list (or just print them)\n3. Test it on a simple tree",
        "starterCode": "class TreeNode:\n    def __init__(self, val): self.val = val; self.left = None; self.right = None\n\ndef inorder(node, result):\n    if node is ___: \n        return\n    \n    # 1. Traverse left\n    inorder(node.___, result)\n    # 2. Visit node\n    result.___(node.val)\n    # 3. Traverse right\n    inorder(node.___, result)\n\nroot = TreeNode(10)\nroot.left = TreeNode(5)\nroot.right = TreeNode(15)\nroot.left.left = TreeNode(2)\nroot.left.right = TreeNode(7)\n\nres = []\ninorder(root, res)\nprint(\"Inorder Traversal:\", res)",
        "solution": "class TreeNode:\n    def __init__(self, val): self.val = val; self.left = None; self.right = None\n\ndef inorder(node, result):\n    if node is None: \n        return\n    \n    # 1. Traverse left\n    inorder(node.left, result)\n    # 2. Visit node\n    result.append(node.val)\n    # 3. Traverse right\n    inorder(node.right, result)\n\nroot = TreeNode(10)\nroot.left = TreeNode(5)\nroot.right = TreeNode(15)\nroot.left.left = TreeNode(2)\nroot.left.right = TreeNode(7)\n\nres = []\ninorder(root, res)\nprint(\"Inorder Traversal:\", res)",
        "hint": "Check if node is None. Recursively call left, append val, recursively call right.",
        "rubric": "Output is [2, 5, 7, 10, 15]. Nodes are sorted!"
      }
    ]
  },
  "Sorting Algorithms": {
    "aiRubric": "Check logic, syntax, and output for Sorting Algorithms.",
    "lessons": [
      {
        "title": "Bubble Sort",
        "theory": "## O(N^2) Complexity\nBubble Sort is a simple but very slow algorithm. It repeatedly steps through the list, compares adjacent elements, and swaps them if they are in the wrong order. It continues until the list is sorted.",
        "instructions": "## Task: Swap Elements\n1. Implement the core mechanic of Bubble Sort: swapping adjacent elements.\n2. Iterate through a list. If element `i` is greater than `i+1`, swap them.\n3. This is just one pass (not the full sort), which moves the largest element to the end.",
        "starterCode": "def bubble_sort_single_pass(arr):\n    # Iterate up to the second-to-last element\n    for i in range(len(arr) - 1):\n        if arr[i] > arr[i + 1]:\n            # Swap them using Python's tuple unpacking\n            arr[i], arr[___] = arr[___], arr[i]\n    return arr\n\nmy_list = [5, 3, 8, 2, 1]\nprint(\"Original:\", my_list)\n\n# One pass\nresult = bubble_sort_single_pass(my_list)\nprint(\"After 1 Pass:\", result)\nprint(\"(Notice how the largest number, 8, 'bubbled' to the end!)\")",
        "solution": "def bubble_sort_single_pass(arr):\n    # Iterate up to the second-to-last element\n    for i in range(len(arr) - 1):\n        if arr[i] > arr[i + 1]:\n            # Swap them using Python's tuple unpacking\n            arr[i], arr[i + 1] = arr[i + 1], arr[i]\n    return arr\n\nmy_list = [5, 3, 8, 2, 1]\nprint(\"Original:\", my_list)\n\n# One pass\nresult = bubble_sort_single_pass(my_list)\nprint(\"After 1 Pass:\", result)\nprint(\"(Notice how the largest number, 8, 'bubbled' to the end!)\")",
        "hint": "arr[i], arr[i + 1] = arr[i + 1], arr[i]",
        "rubric": "Successfully swaps elements. Result is [3, 5, 2, 1, 8]."
      }
    ]
  },
  "Dynamic Programming": {
    "aiRubric": "Check logic, syntax, and output for Dynamic Programming.",
    "lessons": [
      {
        "title": "Memoization",
        "theory": "## Remembering Past Results\nDynamic Programming (DP) optimizes recursive algorithms by storing the results of expensive function calls.\n\nFibonacci is the classic example:\n```python\n# Slow (O(2^n))\ndef fib(n):\n    if n <= 1: return n\n    return fib(n-1) + fib(n-2)\n```\nIf we compute `fib(5)`, we compute `fib(3)` multiple times. DP fixes this.",
        "instructions": "## Task: Memoized Fibonacci\n1. Implement Fibonacci using a dictionary (memo) to cache results\n2. Check if `n` is in `memo`. If so, return it.\n3. Otherwise, compute it, save it to `memo`, and return it",
        "starterCode": "def fib_memo(n, memo=None):\n    if memo is None: memo = {}\n    \n    if n in ___:\n        return memo[n]\n    if n <= 1:\n        return n\n        \n    # Compute and save\n    result = fib_memo(n-1, memo) + fib_memo(n-2, memo)\n    ___[n] = result\n    \n    return result\n\nprint(\"Fib(10):\", fib_memo(10))\nprint(\"Fib(50):\", fib_memo(50)) # Would take years without memoization!",
        "solution": "def fib_memo(n, memo=None):\n    if memo is None: memo = {}\n    \n    if n in memo:\n        return memo[n]\n    if n <= 1:\n        return n\n        \n    # Compute and save\n    result = fib_memo(n-1, memo) + fib_memo(n-2, memo)\n    memo[n] = result\n    \n    return result\n\nprint(\"Fib(10):\", fib_memo(10))\nprint(\"Fib(50):\", fib_memo(50)) # Would take years without memoization!",
        "hint": "Check `if n in memo`. Save to `memo[n] = result`.",
        "rubric": "Fib(50) computes instantly due to memoization."
      }
    ]
  },
  "Tries": {
    "aiRubric": "Check logic, syntax, and output for Tries.",
    "lessons": [
      {
        "title": "Prefix Trees",
        "theory": "## Autocomplete Engine\nA Trie (pronounced 'try') is a tree-like data structure used for efficient string searching. It's the engine behind 'Autocomplete' when you type in a search bar.\n\nInstead of storing whole words, it stores individual characters in nodes. Words sharing a prefix (like 'car' and 'cat') share the same branch ('c' -> 'a').",
        "instructions": "## Task: Insert a Word\n1. Build a basic Trie structure using nested dictionaries.\n2. Insert the word 'cat' into the Trie.",
        "starterCode": "class SimpleTrie:\n    def __init__(self):\n        self.root = {}\n        \n    def insert(self, word):\n        current_node = self.root\n        for char in word:\n            if char not in current_node:\n                # Create a new empty dict for this character\n                current_node[char] = {}\n            # Move down the tree\n            current_node = current_node[___]\n        # Mark the end of the word\n        current_node['*'] = True\n\ntrie = SimpleTrie()\ntrie.insert(\"cat\")\ntrie.insert(\"car\")\n\n# Should output a nested dict structure sharing 'c' and 'a'\nprint(\"Trie Structure:\")\nimport json\nprint(json.dumps(trie.root, indent=2))",
        "solution": "class SimpleTrie:\n    def __init__(self):\n        self.root = {}\n        \n    def insert(self, word):\n        current_node = self.root\n        for char in word:\n            if char not in current_node:\n                # Create a new empty dict for this character\n                current_node[char] = {}\n            # Move down the tree\n            current_node = current_node[char]\n        # Mark the end of the word\n        current_node['*'] = True\n\ntrie = SimpleTrie()\ntrie.insert(\"cat\")\ntrie.insert(\"car\")\n\n# Should output a nested dict structure sharing 'c' and 'a'\nprint(\"Trie Structure:\")\nimport json\nprint(json.dumps(trie.root, indent=2))",
        "hint": "Move down by setting current_node = current_node[char].",
        "rubric": "Trie correctly builds a nested dict sharing 'c' and 'a', branching at 't' and 'r'."
      }
    ]
  },
  "Graph Traversal": {
    "aiRubric": "Check logic, syntax, and output for Graph Traversal.",
    "lessons": [
      {
        "title": "BFS vs DFS",
        "theory": "## Searching a Network\nHow do you find the shortest path in a maze? Or the degrees of separation between two people on LinkedIn?\n\n- **BFS (Breadth-First Search)**: Searches layer by layer (neighbors first). Guarantees the shortest path. Uses a Queue.\n- **DFS (Depth-First Search)**: Explores as far as possible down one branch before backtracking. Uses a Stack (or recursion).",
        "instructions": "## Task: BFS Queue\n1. Simulate a Breadth-First Search using a Queue (list).\n2. Start at Node 'A'. Visit its neighbors before moving deeper.",
        "starterCode": "graph = {\n    'A': ['B', 'C'],\n    'B': ['D', 'E'],\n    'C': ['F'],\n    'D': [], 'E': [], 'F': []\n}\n\ndef bfs(graph, start):\n    queue = [start]\n    visited = set()\n    \n    while queue:\n        # Pop the first element (FIFO)\n        node = queue.pop(___)\n        \n        if node not in visited:\n            print(f\"Visiting: {node}\")\n            visited.add(___)\n            \n            # Add neighbors to the queue\n            for neighbor in graph[node]:\n                queue.append(___)\n\nprint(\"BFS Traversal Order:\")\nbfs(graph, 'A')",
        "solution": "graph = {\n    'A': ['B', 'C'],\n    'B': ['D', 'E'],\n    'C': ['F'],\n    'D': [], 'E': [], 'F': []\n}\n\ndef bfs(graph, start):\n    queue = [start]\n    visited = set()\n    \n    while queue:\n        # Pop the first element (FIFO)\n        node = queue.pop(0)\n        \n        if node not in visited:\n            print(f\"Visiting: {node}\")\n            visited.add(node)\n            \n            # Add neighbors to the queue\n            for neighbor in graph[node]:\n                queue.append(neighbor)\n\nprint(\"BFS Traversal Order:\")\nbfs(graph, 'A')",
        "hint": "queue.pop(0) for FIFO. visited.add(node). queue.append(neighbor).",
        "rubric": "Visits in layer order: A, B, C, D, E, F."
      }
    ]
  }
}